{"index":149,"borderPoints":[],"sides":[{"points":[],"classifiers":{"Bywulf\\Jigsawlutioner\\SideClassifier\\DirectionClassifier":-1,"Bywulf\\Jigsawlutioner\\SideClassifier\\BigWidthClassifier":{"direction":-1,"width":85.97338102857273,"centerPoint":{"x":-40.61805680932791,"y":-60.471830514308884}},"Bywulf\\Jigsawlutioner\\SideClassifier\\SmallWidthClassifier":{"direction":-1,"width":63.7746707876141,"centerPoint":{"x":-32.72544136437865,"y":-17.99187262310484}},"Bywulf\\Jigsawlutioner\\SideClassifier\\CornerDistanceClassifier":297.5533565597915,"Bywulf\\Jigsawlutioner\\SideClassifier\\DepthClassifier":-94.49297333881948},"startPoint":{"x":345,"y":283,"derivative":-80.98067756861826,"index":279,"extreme":true,"usedAsCorner":true},"endPoint":{"x":148,"y":506,"derivative":-85.44783663000757,"index":913,"extreme":true,"usedAsCorner":true}},{"points":[],"classifiers":{"Bywulf\\Jigsawlutioner\\SideClassifier\\DirectionClassifier":-1,"Bywulf\\Jigsawlutioner\\SideClassifier\\BigWidthClassifier":{"direction":-1,"width":100.64409277613318,"centerPoint":{"x":-20.496292446646358,"y":-75.11869246502991}},"Bywulf\\Jigsawlutioner\\SideClassifier\\SmallWidthClassifier":{"direction":-1,"width":58.843856985523864,"centerPoint":{"x":-19.26225403025889,"y":-26.88363539963752}},"Bywulf\\Jigsawlutioner\\SideClassifier\\CornerDistanceClassifier":331.65192597058524,"Bywulf\\Jigsawlutioner\\SideClassifier\\DepthClassifier":-107.16797809844886},"startPoint":{"x":148,"y":506,"derivative":-85.44783663000757,"index":913,"extreme":true,"usedAsCorner":true},"endPoint":{"x":380,"y":743,"derivative":-85.44783663000759,"index":1632,"extreme":true,"usedAsCorner":true}},{"points":[],"classifiers":{"Bywulf\\Jigsawlutioner\\SideClassifier\\DirectionClassifier":-1,"Bywulf\\Jigsawlutioner\\SideClassifier\\BigWidthClassifier":{"direction":-1,"width":100.3860951275959,"centerPoint":{"x":37.66306902501149,"y":-62.07970535201876}},"Bywulf\\Jigsawlutioner\\SideClassifier\\SmallWidthClassifier":{"direction":-1,"width":68.22598078144962,"centerPoint":{"x":35.58227602658372,"y":-19.950169654830916}},"Bywulf\\Jigsawlutioner\\SideClassifier\\CornerDistanceClassifier":368.2281901212882,"Bywulf\\Jigsawlutioner\\SideClassifier\\DepthClassifier":-99.86941016027504},"startPoint":{"x":380,"y":743,"derivative":-85.44783663000759,"index":1632,"extreme":true,"usedAsCorner":true},"endPoint":{"x":626,"y":469,"derivative":-90,"index":2386,"extreme":true,"usedAsCorner":true}},{"points":[],"classifiers":{"Bywulf\\Jigsawlutioner\\SideClassifier\\DirectionClassifier":1,"Bywulf\\Jigsawlutioner\\SideClassifier\\BigWidthClassifier":{"direction":1,"width":92.18839795161969,"centerPoint":{"x":9.329876473514346,"y":66.88819084494206}},"Bywulf\\Jigsawlutioner\\SideClassifier\\SmallWidthClassifier":{"direction":1,"width":69.86679146131225,"centerPoint":{"x":11.4677968255947,"y":22.95582393445414}},"Bywulf\\Jigsawlutioner\\SideClassifier\\CornerDistanceClassifier":336.98219537536403,"Bywulf\\Jigsawlutioner\\SideClassifier\\DepthClassifier":100.97149228820325},"startPoint":{"x":626,"y":469,"derivative":-90,"index":2386,"extreme":true,"usedAsCorner":true},"endPoint":{"x":345,"y":283,"derivative":-80.98067756861826,"index":279,"extreme":true,"usedAsCorner":true}}],"imageWidth":909,"imageHeight":1000}