{"index":343,"borderPoints":[],"sides":[{"points":[],"classifiers":{"Bywulf\\Jigsawlutioner\\SideClassifier\\DirectionClassifier":-1,"Bywulf\\Jigsawlutioner\\SideClassifier\\BigWidthClassifier":{"direction":-1,"width":94.47299853102666,"centerPoint":{"x":22.02314304902157,"y":-76.61626444073637}},"Bywulf\\Jigsawlutioner\\SideClassifier\\SmallWidthClassifier":{"direction":-1,"width":55.98064614829199,"centerPoint":{"x":24.933957926573303,"y":-23.173791195428798}},"Bywulf\\Jigsawlutioner\\SideClassifier\\CornerDistanceClassifier":317.91822848021684,"Bywulf\\Jigsawlutioner\\SideClassifier\\DepthClassifier":-114.8783307781996},"startPoint":{"x":329,"y":187,"derivative":-90,"index":0,"extreme":true,"usedAsCorner":true},"endPoint":{"x":213,"y":483,"derivative":-92.37887222352357,"index":686,"extreme":true,"usedAsCorner":true}},{"points":[],"classifiers":{"Bywulf\\Jigsawlutioner\\SideClassifier\\DirectionClassifier":1,"Bywulf\\Jigsawlutioner\\SideClassifier\\BigWidthClassifier":{"direction":1,"width":103.44454656576019,"centerPoint":{"x":-11.853465453787521,"y":70.25853870203119}},"Bywulf\\Jigsawlutioner\\SideClassifier\\SmallWidthClassifier":{"direction":1,"width":69.55627802206311,"centerPoint":{"x":-11.737347755940057,"y":25.02440965135409}},"Bywulf\\Jigsawlutioner\\SideClassifier\\CornerDistanceClassifier":303.9901314187683,"Bywulf\\Jigsawlutioner\\SideClassifier\\DepthClassifier":98.89988788540703},"startPoint":{"x":213,"y":483,"derivative":-92.37887222352357,"index":686,"extreme":true,"usedAsCorner":true},"endPoint":{"x":496,"y":594,"derivative":-91.48786752882779,"index":1314,"extreme":true,"usedAsCorner":true}},{"points":[],"classifiers":{"Bywulf\\Jigsawlutioner\\SideClassifier\\DirectionClassifier":-1,"Bywulf\\Jigsawlutioner\\SideClassifier\\BigWidthClassifier":{"direction":-1,"width":77.71543502843603,"centerPoint":{"x":-37.44743514879969,"y":-59.83105122488378}},"Bywulf\\Jigsawlutioner\\SideClassifier\\SmallWidthClassifier":{"direction":-1,"width":67.0348021948719,"centerPoint":{"x":-28.88802753600853,"y":-28.77396537842091}},"Bywulf\\Jigsawlutioner\\SideClassifier\\CornerDistanceClassifier":342.34777639120136,"Bywulf\\Jigsawlutioner\\SideClassifier\\DepthClassifier":-93.09741301776187},"startPoint":{"x":496,"y":594,"derivative":-91.48786752882779,"index":1314,"extreme":true,"usedAsCorner":true},"endPoint":{"x":615,"y":273,"derivative":-91.91446645445332,"index":1930,"extreme":true,"usedAsCorner":true}},{"points":[],"classifiers":{"Bywulf\\Jigsawlutioner\\SideClassifier\\DirectionClassifier":-1,"Bywulf\\Jigsawlutioner\\SideClassifier\\BigWidthClassifier":{"direction":-1,"width":88.7789576770685,"centerPoint":{"x":-33.257625678175536,"y":-59.95389954192351}},"Bywulf\\Jigsawlutioner\\SideClassifier\\SmallWidthClassifier":{"direction":-1,"width":66.46389782023401,"centerPoint":{"x":-33.90830710623613,"y":-19.853034955142157}},"Bywulf\\Jigsawlutioner\\SideClassifier\\CornerDistanceClassifier":298.6502971704532,"Bywulf\\Jigsawlutioner\\SideClassifier\\DepthClassifier":-89.41457977118367},"startPoint":{"x":615,"y":273,"derivative":-91.91446645445332,"index":1930,"extreme":true,"usedAsCorner":true},"endPoint":{"x":329,"y":187,"derivative":-90,"index":0,"extreme":true,"usedAsCorner":true}}],"imageWidth":909,"imageHeight":1000}