{"index":126,"borderPoints":[],"sides":[{"points":[],"classifiers":{"Bywulf\\Jigsawlutioner\\SideClassifier\\DirectionClassifier":1,"Bywulf\\Jigsawlutioner\\SideClassifier\\BigWidthClassifier":{"direction":1,"width":98.35537215442702,"centerPoint":{"x":-7.389350244164461,"y":74.66773229007023}},"Bywulf\\Jigsawlutioner\\SideClassifier\\SmallWidthClassifier":{"direction":1,"width":57.037132699505065,"centerPoint":{"x":-8.742938913822726,"y":22.29669576745184}},"Bywulf\\Jigsawlutioner\\SideClassifier\\CornerDistanceClassifier":306.8941185490527,"Bywulf\\Jigsawlutioner\\SideClassifier\\DepthClassifier":106.79940688173599},"startPoint":{"x":256,"y":639,"derivative":-90.00000000000001,"index":712,"extreme":true,"usedAsCorner":true},"endPoint":{"x":534,"y":769,"derivative":-81.5110561194953,"index":1378,"extreme":true,"usedAsCorner":true}},{"points":[],"classifiers":{"Bywulf\\Jigsawlutioner\\SideClassifier\\DirectionClassifier":-1,"Bywulf\\Jigsawlutioner\\SideClassifier\\BigWidthClassifier":{"direction":-1,"width":106.63445819970869,"centerPoint":{"x":4.792936591178858,"y":-73.10086666509861}},"Bywulf\\Jigsawlutioner\\SideClassifier\\SmallWidthClassifier":{"direction":-1,"width":63.08195051745207,"centerPoint":{"x":4.5567047260999445,"y":-17.694236464792446}},"Bywulf\\Jigsawlutioner\\SideClassifier\\CornerDistanceClassifier":334.5160683734042,"Bywulf\\Jigsawlutioner\\SideClassifier\\DepthClassifier":-105.13744809286105},"startPoint":{"x":534,"y":769,"derivative":-81.5110561194953,"index":1378,"extreme":true,"usedAsCorner":true},"endPoint":{"x":684,"y":470,"derivative":-90,"index":2095,"extreme":true,"usedAsCorner":true}},{"points":[],"classifiers":{"Bywulf\\Jigsawlutioner\\SideClassifier\\DirectionClassifier":0,"Bywulf\\Jigsawlutioner\\SideClassifier\\CornerDistanceClassifier":291.6504757410829},"startPoint":{"x":684,"y":470,"derivative":-90,"index":2095,"extreme":true,"usedAsCorner":true},"endPoint":{"x":426,"y":334,"derivative":-90,"index":2489,"extreme":true,"usedAsCorner":true}},{"points":[],"classifiers":{"Bywulf\\Jigsawlutioner\\SideClassifier\\DirectionClassifier":-1,"Bywulf\\Jigsawlutioner\\SideClassifier\\BigWidthClassifier":{"direction":-1,"width":89.08974162121271,"centerPoint":{"x":-11.573529044970236,"y":-67.2678866780193}},"Bywulf\\Jigsawlutioner\\SideClassifier\\SmallWidthClassifier":{"direction":-1,"width":50.79260439152314,"centerPoint":{"x":-10.02803712193711,"y":-23.175151850003147}},"Bywulf\\Jigsawlutioner\\SideClassifier\\CornerDistanceClassifier":349.1776052383658,"Bywulf\\Jigsawlutioner\\SideClassifier\\DepthClassifier":-97.18233363091464},"startPoint":{"x":426,"y":334,"derivative":-90,"index":2489,"extreme":true,"usedAsCorner":true},"endPoint":{"x":256,"y":639,"derivative":-90.00000000000001,"index":712,"extreme":true,"usedAsCorner":true}}],"imageWidth":909,"imageHeight":1000}