{"index":293,"borderPoints":[],"sides":[{"points":[],"classifiers":{"Bywulf\\Jigsawlutioner\\SideClassifier\\DirectionClassifier":1,"Bywulf\\Jigsawlutioner\\SideClassifier\\BigWidthClassifier":{"direction":1,"width":84.9007735544095,"centerPoint":{"x":1.7210636150037217,"y":71.38959025810829}},"Bywulf\\Jigsawlutioner\\SideClassifier\\SmallWidthClassifier":{"direction":1,"width":62.59381431309784,"centerPoint":{"x":-7.707041892093628,"y":28.16946347909628}},"Bywulf\\Jigsawlutioner\\SideClassifier\\CornerDistanceClassifier":313.98407602934077,"Bywulf\\Jigsawlutioner\\SideClassifier\\DepthClassifier":101.17258998986163},"startPoint":{"x":490,"y":308,"derivative":-94.58122008527704,"index":0,"extreme":true,"usedAsCorner":true},"endPoint":{"x":265,"y":527,"derivative":-85.41877991472296,"index":654,"extreme":true,"usedAsCorner":true}},{"points":[],"classifiers":{"Bywulf\\Jigsawlutioner\\SideClassifier\\DirectionClassifier":-1,"Bywulf\\Jigsawlutioner\\SideClassifier\\BigWidthClassifier":{"direction":-1,"width":100.0005097665482,"centerPoint":{"x":-11.629850808947907,"y":-65.80275233273042}},"Bywulf\\Jigsawlutioner\\SideClassifier\\SmallWidthClassifier":{"direction":-1,"width":66.11200710524099,"centerPoint":{"x":-12.1577191951244,"y":-20.96267684070805}},"Bywulf\\Jigsawlutioner\\SideClassifier\\CornerDistanceClassifier":290.6888370749718,"Bywulf\\Jigsawlutioner\\SideClassifier\\DepthClassifier":-99.29276317061493},"startPoint":{"x":265,"y":527,"derivative":-85.41877991472296,"index":654,"extreme":true,"usedAsCorner":true},"endPoint":{"x":455,"y":747,"derivative":-90,"index":1302,"extreme":true,"usedAsCorner":true}},{"points":[],"classifiers":{"Bywulf\\Jigsawlutioner\\SideClassifier\\DirectionClassifier":1,"Bywulf\\Jigsawlutioner\\SideClassifier\\BigWidthClassifier":{"direction":1,"width":72.82041556267208,"centerPoint":{"x":20.06381647419387,"y":59.44278246661344}},"Bywulf\\Jigsawlutioner\\SideClassifier\\SmallWidthClassifier":{"direction":1,"width":54.832613085810834,"centerPoint":{"x":20.809650294301406,"y":23.94232618959928}},"Bywulf\\Jigsawlutioner\\SideClassifier\\CornerDistanceClassifier":307.7174028227842,"Bywulf\\Jigsawlutioner\\SideClassifier\\DepthClassifier":86.57626311400958},"startPoint":{"x":455,"y":747,"derivative":-90,"index":1302,"extreme":true,"usedAsCorner":true},"endPoint":{"x":688,"y":546,"derivative":-90,"index":1954,"extreme":true,"usedAsCorner":true}},{"points":[],"classifiers":{"Bywulf\\Jigsawlutioner\\SideClassifier\\DirectionClassifier":-1,"Bywulf\\Jigsawlutioner\\SideClassifier\\BigWidthClassifier":{"direction":-1,"width":88.39823792870732,"centerPoint":{"x":34.96242924451623,"y":-63.96671308966739}},"Bywulf\\Jigsawlutioner\\SideClassifier\\SmallWidthClassifier":{"direction":-1,"width":67.22855387557976,"centerPoint":{"x":35.16036104324362,"y":-18.44985217056177}},"Bywulf\\Jigsawlutioner\\SideClassifier\\CornerDistanceClassifier":309.5932815808508,"Bywulf\\Jigsawlutioner\\SideClassifier\\DepthClassifier":-91.33795018332485},"startPoint":{"x":688,"y":546,"derivative":-90,"index":1954,"extreme":true,"usedAsCorner":true},"endPoint":{"x":490,"y":308,"derivative":-94.58122008527704,"index":0,"extreme":true,"usedAsCorner":true}}],"imageWidth":909,"imageHeight":1000}