{"index":118,"borderPoints":[],"sides":[{"points":[],"classifiers":{"Bywulf\\Jigsawlutioner\\SideClassifier\\DirectionClassifier":-1,"Bywulf\\Jigsawlutioner\\SideClassifier\\BigWidthClassifier":{"direction":-1,"width":99.16990094335401,"centerPoint":{"x":3.5668440129182954,"y":-63.804701258295374}},"Bywulf\\Jigsawlutioner\\SideClassifier\\SmallWidthClassifier":{"direction":-1,"width":64.32251059704072,"centerPoint":{"x":3.7241868163644156,"y":-17.039206154240905}},"Bywulf\\Jigsawlutioner\\SideClassifier\\CornerDistanceClassifier":309.5351353239241,"Bywulf\\Jigsawlutioner\\SideClassifier\\DepthClassifier":-96.46471430556191},"startPoint":{"x":242,"y":442,"derivative":-85.6676860168115,"index":446,"extreme":true,"usedAsCorner":true},"endPoint":{"x":416,"y":698,"derivative":-85.53284093861072,"index":1112,"extreme":true,"usedAsCorner":true}},{"points":[],"classifiers":{"Bywulf\\Jigsawlutioner\\SideClassifier\\DirectionClassifier":1,"Bywulf\\Jigsawlutioner\\SideClassifier\\BigWidthClassifier":{"direction":1,"width":97.0163611484544,"centerPoint":{"x":-4.1902462475674085,"y":65.73462593170707}},"Bywulf\\Jigsawlutioner\\SideClassifier\\SmallWidthClassifier":{"direction":1,"width":69.88936006018663,"centerPoint":{"x":-1.7483700654744752,"y":27.170087391522863}},"Bywulf\\Jigsawlutioner\\SideClassifier\\CornerDistanceClassifier":347.4046631811366,"Bywulf\\Jigsawlutioner\\SideClassifier\\DepthClassifier":100.79941581065579},"startPoint":{"x":416,"y":698,"derivative":-85.53284093861072,"index":1112,"extreme":true,"usedAsCorner":true},"endPoint":{"x":695,"y":491,"derivative":-90,"index":1818,"extreme":true,"usedAsCorner":true}},{"points":[],"classifiers":{"Bywulf\\Jigsawlutioner\\SideClassifier\\DirectionClassifier":-1,"Bywulf\\Jigsawlutioner\\SideClassifier\\BigWidthClassifier":{"direction":-1,"width":107.3673716234415,"centerPoint":{"x":23.85891521623341,"y":-65.5622741152601}},"Bywulf\\Jigsawlutioner\\SideClassifier\\SmallWidthClassifier":{"direction":-1,"width":66.59552866114618,"centerPoint":{"x":16.966566009848314,"y":-17.65568543241171}},"Bywulf\\Jigsawlutioner\\SideClassifier\\CornerDistanceClassifier":301.44485399488906,"Bywulf\\Jigsawlutioner\\SideClassifier\\DepthClassifier":-99.71121337800005},"startPoint":{"x":695,"y":491,"derivative":-90,"index":1818,"extreme":true,"usedAsCorner":true},"endPoint":{"x":510,"y":253,"derivative":-94.5521633699924,"index":2493,"extreme":true,"usedAsCorner":true}},{"points":[],"classifiers":{"Bywulf\\Jigsawlutioner\\SideClassifier\\DirectionClassifier":1,"Bywulf\\Jigsawlutioner\\SideClassifier\\BigWidthClassifier":{"direction":1,"width":82.74715771587562,"centerPoint":{"x":-37.37383712255144,"y":73.00088244721434}},"Bywulf\\Jigsawlutioner\\SideClassifier\\SmallWidthClassifier":{"direction":1,"width":53.4383352768784,"centerPoint":{"x":-38.42104754283919,"y":22.921803618608713}},"Bywulf\\Jigsawlutioner\\SideClassifier\\CornerDistanceClassifier":327.9405433916337,"Bywulf\\Jigsawlutioner\\SideClassifier\\DepthClassifier":105.18608880044357},"startPoint":{"x":510,"y":253,"derivative":-94.5521633699924,"index":2493,"extreme":true,"usedAsCorner":true},"endPoint":{"x":242,"y":442,"derivative":-85.6676860168115,"index":446,"extreme":true,"usedAsCorner":true}}],"imageWidth":909,"imageHeight":1000}